chessplotlib/__init__.py
chessplotlib/pgn.py
chessplotlib/plot.py
chessplotlib-1.0.2.data/scripts/pgn-viewer
chessplotlib-1.0.2.dist-info/LICENSE
chessplotlib-1.0.2.dist-info/METADATA
chessplotlib-1.0.2.dist-info/WHEEL
chessplotlib-1.0.2.dist-info/top_level.txt
chessplotlib-1.0.2.dist-info/RECORD
