Metadata-Version: 2.1
Name: chessplotlib
Version: 1.0.2
Summary: Chess plots with matplotlib
Home-page: UNKNOWN
License: UNKNOWN
Platform: UNKNOWN
Requires-Python: >=3
License-File: LICENSE
Requires-Dist: matplotlib
Requires-Dist: numpy
Requires-Dist: chess
